{
  "A": {
    "checks": {
      "G": {
        "backend": "fast",
        "codewords_checked": 63,
        "d_est": 48,
        "d_signed": null,
        "d_witness": 48,
        "early_stop": false,
        "exact": true,
        "k": 6,
        "rank": 90,
        "seed": 2127362876
      },
      "H": {
        "backend": "fast",
        "codewords_checked": 63,
        "d_est": 48,
        "d_signed": null,
        "d_witness": 48,
        "early_stop": false,
        "exact": true,
        "k": 6,
        "rank": 90,
        "seed": 796001121
      }
    },
    "d_est": 48,
    "elements": [
      0,
      2,
      3,
      6,
      9,
      15
    ],
    "elements_repr": [
      "0",
      "2",
      "3",
      "6",
      "9",
      "15"
    ],
    "group": {
      "order": 16,
      "spec": "SmallGroup(16,1)"
    },
    "id": "Ap20_0-2-3-6-9-15",
    "k_classical": 6,
    "passes": true,
    "perm_idx": 20,
    "side": "A",
    "slice_codes": {
      "A_G": {
        "backend": "fast",
        "d_ub": 48,
        "d_witness": 48,
        "exact": true,
        "k": 6,
        "n": 96
      },
      "A_H": {
        "backend": "fast",
        "d_ub": 48,
        "d_witness": 48,
        "exact": true,
        "k": 6,
        "n": 96
      }
    },
    "slice_n": 96
  },
  "B": {
    "checks": {
      "Gp": {
        "backend": "fast",
        "codewords_checked": 63,
        "d_est": 48,
        "d_signed": null,
        "d_witness": 48,
        "early_stop": false,
        "exact": true,
        "k": 6,
        "rank": 90,
        "seed": 2137870479
      },
      "Hp": {
        "backend": "fast",
        "codewords_checked": 63,
        "d_est": 48,
        "d_signed": null,
        "d_witness": 48,
        "early_stop": false,
        "exact": true,
        "k": 6,
        "rank": 90,
        "seed": 2084734869
      }
    },
    "d_est": 48,
    "elements": [
      0,
      1,
      2,
      3,
      5,
      9
    ],
    "elements_repr": [
      "0",
      "1",
      "2",
      "3",
      "5",
      "9"
    ],
    "group": {
      "order": 16,
      "spec": "SmallGroup(16,1)"
    },
    "id": "Bp20_0-1-2-3-5-9",
    "k_classical": 6,
    "passes": true,
    "perm_idx": 20,
    "side": "B",
    "slice_codes": {
      "B_G": {
        "backend": "fast",
        "d_ub": 48,
        "d_witness": 48,
        "exact": true,
        "k": 6,
        "n": 96
      },
      "B_H": {
        "backend": "fast",
        "d_ub": 48,
        "d_witness": 48,
        "exact": true,
        "k": 6,
        "n": 96
      }
    },
    "slice_n": 96
  },
  "classical_slices": {
    "A_G": {
      "backend": "fast",
      "d_ub": 48,
      "d_witness": 48,
      "exact": true,
      "k": 6,
      "n": 96
    },
    "A_H": {
      "backend": "fast",
      "d_ub": 48,
      "d_witness": 48,
      "exact": true,
      "k": 6,
      "n": 96
    },
    "B_G": {
      "backend": "fast",
      "d_ub": 48,
      "d_witness": 48,
      "exact": true,
      "k": 6,
      "n": 96
    },
    "B_H": {
      "backend": "fast",
      "d_ub": 48,
      "d_witness": 48,
      "exact": true,
      "k": 6,
      "n": 96
    }
  },
  "code_id": "SmallGroup_16_1__AAp20_0_2_3_6_9_15_BBp20_0_1_2_3_5_9_k12_d47",
  "distance": {
    "dX_best": 47,
    "dZ_best": 47,
    "d_ub": 47,
    "fast": {
      "dx": {
        "d_ub": 68,
        "early_stop": false,
        "seed": 83288583,
        "signed": 68,
        "steps": 4000
      },
      "dz": {
        "d_ub": 64,
        "early_stop": false,
        "seed": 1733848101,
        "signed": 64,
        "steps": 4000
      }
    },
    "method": "dist_m4ri_rw_progressive",
    "refine_chunk": 20000,
    "refine_chunks": [
      {
        "chunk": 1,
        "d_x_best": 64,
        "d_z_best": 59,
        "dx": {
          "d_ub": 64,
          "early_stop": false,
          "seed": 564069715,
          "signed": 64,
          "steps": 20000
        },
        "dz": {
          "d_ub": 59,
          "early_stop": false,
          "seed": 1852777219,
          "signed": 59,
          "steps": 20000
        },
        "steps": 20000
      },
      {
        "chunk": 2,
        "d_x_best": 58,
        "d_z_best": 59,
        "dx": {
          "d_ub": 58,
          "early_stop": false,
          "seed": 188400442,
          "signed": 58,
          "steps": 20000
        },
        "dz": {
          "d_ub": 64,
          "early_stop": false,
          "seed": 1909643012,
          "signed": 64,
          "steps": 20000
        },
        "steps": 20000
      },
      {
        "chunk": 3,
        "d_x_best": 58,
        "d_z_best": 59,
        "dx": {
          "d_ub": 59,
          "early_stop": false,
          "seed": 813936252,
          "signed": 59,
          "steps": 20000
        },
        "dz": {
          "d_ub": 67,
          "early_stop": false,
          "seed": 1364661797,
          "signed": 67,
          "steps": 20000
        },
        "steps": 20000
      },
      {
        "chunk": 4,
        "d_x_best": 47,
        "d_z_best": 59,
        "dx": {
          "d_ub": 47,
          "early_stop": false,
          "seed": 1737796682,
          "signed": 47,
          "steps": 20000
        },
        "dz": {
          "d_ub": 60,
          "early_stop": false,
          "seed": 327655845,
          "signed": 60,
          "steps": 20000
        },
        "steps": 20000
      },
      {
        "chunk": 5,
        "d_x_best": 47,
        "d_z_best": 59,
        "dx": {
          "d_ub": 64,
          "early_stop": false,
          "seed": 703949795,
          "signed": 64,
          "steps": 20000
        },
        "dz": {
          "d_ub": 62,
          "early_stop": false,
          "seed": 1171020401,
          "signed": 62,
          "steps": 20000
        },
        "steps": 20000
      },
      {
        "chunk": 6,
        "d_x_best": 47,
        "d_z_best": 55,
        "dx": {
          "d_ub": 56,
          "early_stop": false,
          "seed": 690980457,
          "signed": 56,
          "steps": 20000
        },
        "dz": {
          "d_ub": 55,
          "early_stop": false,
          "seed": 446776638,
          "signed": 55,
          "steps": 20000
        },
        "steps": 20000
      },
      {
        "chunk": 7,
        "d_x_best": 47,
        "d_z_best": 55,
        "dx": {
          "d_ub": 59,
          "early_stop": false,
          "seed": 1955130650,
          "signed": 59,
          "steps": 20000
        },
        "dz": {
          "d_ub": 60,
          "early_stop": false,
          "seed": 42597843,
          "signed": 60,
          "steps": 20000
        },
        "steps": 20000
      },
      {
        "chunk": 8,
        "d_x_best": 47,
        "d_z_best": 55,
        "dx": {
          "d_ub": 57,
          "early_stop": false,
          "seed": 1952853210,
          "signed": 57,
          "steps": 20000
        },
        "dz": {
          "d_ub": 64,
          "early_stop": false,
          "seed": 974624864,
          "signed": 64,
          "steps": 20000
        },
        "steps": 20000
      },
      {
        "chunk": 9,
        "d_x_best": 47,
        "d_z_best": 55,
        "dx": {
          "d_ub": 54,
          "early_stop": false,
          "seed": 1887069056,
          "signed": 54,
          "steps": 20000
        },
        "dz": {
          "d_ub": 67,
          "early_stop": false,
          "seed": 643081642,
          "signed": 67,
          "steps": 20000
        },
        "steps": 20000
      },
      {
        "chunk": 10,
        "d_x_best": 47,
        "d_z_best": 48,
        "dx": {
          "d_ub": 59,
          "early_stop": false,
          "seed": 52514399,
          "signed": 59,
          "steps": 20000
        },
        "dz": {
          "d_ub": 48,
          "early_stop": false,
          "seed": 1114330179,
          "signed": 48,
          "steps": 20000
        },
        "steps": 20000
      },
      {
        "chunk": 11,
        "d_x_best": 47,
        "d_z_best": 48,
        "dx": {
          "d_ub": 50,
          "early_stop": false,
          "seed": 498717049,
          "signed": 50,
          "steps": 20000
        },
        "dz": {
          "d_ub": 65,
          "early_stop": false,
          "seed": 559035148,
          "signed": 65,
          "steps": 20000
        },
        "steps": 20000
      },
      {
        "chunk": 12,
        "d_x_best": 47,
        "d_z_best": 48,
        "dx": {
          "d_ub": 61,
          "early_stop": false,
          "seed": 517842788,
          "signed": 61,
          "steps": 20000
        },
        "dz": {
          "d_ub": 59,
          "early_stop": false,
          "seed": 892682524,
          "signed": 59,
          "steps": 20000
        },
        "steps": 20000
      },
      {
        "chunk": 13,
        "d_x_best": 47,
        "d_z_best": 48,
        "dx": {
          "d_ub": 67,
          "early_stop": false,
          "seed": 1713748711,
          "signed": 67,
          "steps": 20000
        },
        "dz": {
          "d_ub": 66,
          "early_stop": false,
          "seed": 575580191,
          "signed": 66,
          "steps": 20000
        },
        "steps": 20000
      },
      {
        "chunk": 14,
        "d_x_best": 47,
        "d_z_best": 48,
        "dx": {
          "d_ub": 66,
          "early_stop": false,
          "seed": 1093276295,
          "signed": 66,
          "steps": 20000
        },
        "dz": {
          "d_ub": 64,
          "early_stop": false,
          "seed": 441204030,
          "signed": 64,
          "steps": 20000
        },
        "steps": 20000
      },
      {
        "chunk": 15,
        "d_x_best": 47,
        "d_z_best": 48,
        "dx": {
          "d_ub": 48,
          "early_stop": false,
          "seed": 210639615,
          "signed": 48,
          "steps": 20000
        },
        "dz": {
          "d_ub": 68,
          "early_stop": false,
          "seed": 1403570809,
          "signed": 68,
          "steps": 20000
        },
        "steps": 20000
      },
      {
        "chunk": 16,
        "d_x_best": 47,
        "d_z_best": 48,
        "dx": {
          "d_ub": 53,
          "early_stop": false,
          "seed": 189452063,
          "signed": 53,
          "steps": 20000
        },
        "dz": {
          "d_ub": 53,
          "early_stop": false,
          "seed": 730704305,
          "signed": 53,
          "steps": 20000
        },
        "steps": 20000
      },
      {
        "chunk": 17,
        "d_x_best": 47,
        "d_z_best": 48,
        "dx": {
          "d_ub": 64,
          "early_stop": false,
          "seed": 1756658023,
          "signed": 64,
          "steps": 20000
        },
        "dz": {
          "d_ub": 52,
          "early_stop": false,
          "seed": 560032509,
          "signed": 52,
          "steps": 20000
        },
        "steps": 20000
      },
      {
        "chunk": 18,
        "d_x_best": 47,
        "d_z_best": 48,
        "dx": {
          "d_ub": 54,
          "early_stop": false,
          "seed": 68318150,
          "signed": 54,
          "steps": 20000
        },
        "dz": {
          "d_ub": 60,
          "early_stop": false,
          "seed": 319187850,
          "signed": 60,
          "steps": 20000
        },
        "steps": 20000
      },
      {
        "chunk": 19,
        "d_x_best": 47,
        "d_z_best": 48,
        "dx": {
          "d_ub": 64,
          "early_stop": false,
          "seed": 2013016435,
          "signed": 64,
          "steps": 20000
        },
        "dz": {
          "d_ub": 60,
          "early_stop": false,
          "seed": 528706906,
          "signed": 60,
          "steps": 20000
        },
        "steps": 20000
      },
      {
        "chunk": 20,
        "d_x_best": 47,
        "d_z_best": 48,
        "dx": {
          "d_ub": 64,
          "early_stop": false,
          "seed": 701427805,
          "signed": 64,
          "steps": 20000
        },
        "dz": {
          "d_ub": 62,
          "early_stop": false,
          "seed": 173399814,
          "signed": 62,
          "steps": 20000
        },
        "steps": 20000
      },
      {
        "chunk": 21,
        "d_x_best": 47,
        "d_z_best": 48,
        "dx": {
          "d_ub": 64,
          "early_stop": false,
          "seed": 476561518,
          "signed": 64,
          "steps": 20000
        },
        "dz": {
          "d_ub": 60,
          "early_stop": false,
          "seed": 1784028261,
          "signed": 60,
          "steps": 20000
        },
        "steps": 20000
      },
      {
        "chunk": 22,
        "d_x_best": 47,
        "d_z_best": 47,
        "dx": {
          "d_ub": 54,
          "early_stop": false,
          "seed": 1809977530,
          "signed": 54,
          "steps": 20000
        },
        "dz": {
          "d_ub": 47,
          "early_stop": false,
          "seed": 81174417,
          "signed": 47,
          "steps": 20000
        },
        "steps": 20000
      },
      {
        "chunk": 23,
        "d_x_best": 47,
        "d_z_best": 47,
        "dx": {
          "d_ub": 54,
          "early_stop": false,
          "seed": 1076478787,
          "signed": 54,
          "steps": 20000
        },
        "dz": {
          "d_ub": 57,
          "early_stop": false,
          "seed": 1084643865,
          "signed": 57,
          "steps": 20000
        },
        "steps": 20000
      },
      {
        "chunk": 24,
        "d_x_best": 47,
        "d_z_best": 47,
        "dx": {
          "d_ub": 64,
          "early_stop": false,
          "seed": 199630338,
          "signed": 64,
          "steps": 20000
        },
        "dz": {
          "d_ub": 64,
          "early_stop": false,
          "seed": 1481939427,
          "signed": 64,
          "steps": 20000
        },
        "steps": 20000
      },
      {
        "chunk": 25,
        "d_x_best": 47,
        "d_z_best": 47,
        "dx": {
          "d_ub": 68,
          "early_stop": false,
          "seed": 744795868,
          "signed": 68,
          "steps": 16000
        },
        "dz": {
          "d_ub": 56,
          "early_stop": false,
          "seed": 1806207348,
          "signed": 56,
          "steps": 16000
        },
        "steps": 16000
      }
    ],
    "steps_fast": 4000,
    "steps_slow": 500000,
    "steps_used_total": 1000000,
    "steps_used_x": 500000,
    "steps_used_z": 500000,
    "wmin": 42
  },
  "group": {
    "order": 16,
    "spec": "SmallGroup(16,1)"
  },
  "k": 12,
  "local_codes": {
    "C0": "hamming_6_3_3_shortened",
    "C0p": "hamming_6_3_3_shortened",
    "C1": "hamming_6_3_3_shortened_var20",
    "C1p": "hamming_6_3_3_shortened_var20",
    "permA_idx": 20,
    "permB_idx": 20
  },
  "n": 576,
  "seed": 1,
  "target_distance": 24
}